hugs/__init__.py
hugs/errors.py
hugs/expression.py
hugs/manager.py
hugs/parser.py
hugs/repository.py
hugs-0.2.0.dist-info/DESCRIPTION.rst
hugs-0.2.0.dist-info/METADATA
hugs-0.2.0.dist-info/RECORD
hugs-0.2.0.dist-info/WHEEL
hugs-0.2.0.dist-info/metadata.json
hugs-0.2.0.dist-info/top_level.txt
