Metadata-Version: 2.0
Name: hugs
Version: 0.2.0
Summary: Hugs lets you map SQL expressions to Python functions.
Home-page: https://github.com/Bogdanp/hugs
Author: Bogdan Popa
Author-email: popa.bogdanp@gmail.com
License: UNKNOWN
Platform: UNKNOWN
